{
  "user_preferences": {
    "Entertainment": 0.0,
    "Documentaries": 0.5,
    "Sports": -0.25,
    "Music": 1.0,
    "Films": 0.5,
    "Signed": 1.5,
    "Science & Nature": -0.5,
    "CBBC": 1.0,
    "From the Archives": -0.25
  },
  "user_interactions": [
    [
      "The Rap Game UK - Extras: UK Rap Artists On How To Make It In The Music Industry",
      "Entertainment",
      "watched",
      25
    ],
    [
      "When Snooker Ruled the World",
      "Entertainment",
      "watched",
      75
    ],
    [
      "We Are England - Belonging: The Real Vicars of Dibley",
      "Documentaries",
      "watched",
      25
    ],
    [
      "The One Show - 22/03/2022",
      "Entertainment",
      "skipped"
    ],
    [
      "The FA Cup - 2021/22: Fifth Round: Southampton v West Ham United",
      "Sports",
      "watched",
      25
    ],
    [
      "Omnibus - Lucian Freud",
      "Documentaries",
      "watched",
      25
    ],
    [
      "ABBA at the BBC",
      "Music",
      "watched",
      75
    ],
    [
      "Apostasy",
      "Films",
      "skipped"
    ],
    [
      "Bitesize Daily: 9-11 Year Olds - English: English - Spoken Language",
      "Signed",
      "watched",
      50
    ],
    [
      "Shark",
      "Science & Nature",
      "skipped"
    ],
    [
      "Movies With Ali Plumb - James McAvoy: Movies That Made Me",
      "Entertainment",
      "watched",
      25
    ],
    [
      "Radio 2 Piano Room Month - The Radio 2 Piano Room",
      "Music",
      "watched",
      50
    ],
    [
      "Pok\u00e9mon: Black and White - Movies: Genesect and the Legend Awakened",
      "CBBC",
      "liked"
    ],
    [
      "Waterhole: Africa's Animal Oasis",
      "Documentaries",
      "watched",
      75
    ],
    [
      "Winter Walks",
      "Documentaries",
      "watched",
      25
    ],
    [
      "We Are England - Made in England: The 007 Shoe Factory - Northampton",
      "Documentaries",
      "watched",
      10
    ],
    [
      "Once Were Brothers: Robbie Robertson and The Band",
      "Documentaries",
      "disliked"
    ],
    [
      "Cutting It",
      "From the Archives",
      "watched",
      10
    ],
    [
      "Rush",
      "Films",
      "liked"
    ],
    [
      "Stacey Dooley Investigates - Shot by My Neighbour",
      "Documentaries",
      "watched",
      10
    ],
    [
      "The Catherine Tate Show - Christmas Special 2007",
      "From the Archives",
      "skipped"
    ],
    [
      "The Outlaw",
      "Films",
      "watched",
      25
    ],
    [
      "Emma",
      "Films",
      "watched",
      25
    ],
    [
      "Modern Times - Streetwise",
      "Documentaries",
      "watched",
      75
    ],
    [
      "Women at Work",
      "From the Archives",
      "watched",
      75
    ],
    [
      "Bellator MMA - 2021: Fedor Emelianenko vs. Timothy Johnson",
      "Sports",
      "watched",
      10
    ],
    [
      "CBeebies Presents - Stage Shows: A Christmas Carol",
      "Signed",
      "watched",
      50
    ],
    [
      "Blue Planet II - Oceans of Wonder",
      "Documentaries",
      "watched",
      75
    ],
    [
      "Leonardo",
      "Documentaries",
      "watched",
      50
    ],
    [
      "Bitesize Daily: 9-11 Year Olds - Wellbeing: 1",
      "Signed",
      "watched",
      75
    ]
  ],
  "watch_counts": {
    "The Rap Game UK - Extras: UK Rap Artists On How To Make It In The Music Industry": 1,
    "When Snooker Ruled the World": 1,
    "We Are England - Belonging: The Real Vicars of Dibley": 1,
    "The FA Cup - 2021/22: Fifth Round: Southampton v West Ham United": 1,
    "Omnibus - Lucian Freud": 1,
    "ABBA at the BBC": 1,
    "Bitesize Daily: 9-11 Year Olds - English: English - Spoken Language": 1,
    "Movies With Ali Plumb - James McAvoy: Movies That Made Me": 1,
    "Radio 2 Piano Room Month - The Radio 2 Piano Room": 1,
    "Pok\u00e9mon: Black and White - Movies: Genesect and the Legend Awakened": 1,
    "Waterhole: Africa's Animal Oasis": 1,
    "Winter Walks": 1,
    "We Are England - Made in England: The 007 Shoe Factory - Northampton": 1,
    "Cutting It": 1,
    "Rush": 1,
    "Stacey Dooley Investigates - Shot by My Neighbour": 1,
    "The Outlaw": 1,
    "Emma": 1,
    "Modern Times - Streetwise": 1,
    "Women at Work": 1,
    "Bellator MMA - 2021: Fedor Emelianenko vs. Timothy Johnson": 1,
    "CBeebies Presents - Stage Shows: A Christmas Carol": 1,
    "Blue Planet II - Oceans of Wonder": 1,
    "Leonardo": 1,
    "Bitesize Daily: 9-11 Year Olds - Wellbeing: 1": 1
  }
}